[
null,
{"id":1,"actions":[{"conditionParam1":0,"conditionParam2":0,"conditionType":0,"rating":5,"skillId":1}],"battlerHue":0,"battlerName":"Rat","dropItems":[{"dataId":1,"denominator":1,"kind":0},{"dataId":1,"denominator":1,"kind":0},{"dataId":1,"denominator":1,"kind":0}],"exp":0,"traits":[{"code":11,"dataId":3,"value":1},{"code":11,"dataId":4,"value":0.5},{"code":11,"dataId":5,"value":1.5},{"code":31,"dataId":3,"value":1},{"code":22,"dataId":0,"value":1}],"gold":0,"name":"オーラット【α】","note":"","params":[85,0,20,10,10,10,10,10]},
{"id":2,"actions":[{"conditionParam1":0,"conditionParam2":0,"conditionType":0,"rating":5,"skillId":1}],"battlerHue":0,"battlerName":"","dropItems":[{"dataId":1,"denominator":1,"kind":0},{"dataId":1,"denominator":1,"kind":0},{"dataId":1,"denominator":1,"kind":0}],"exp":0,"traits":[{"code":22,"dataId":0,"value":0.95},{"code":22,"dataId":1,"value":0.05},{"code":31,"dataId":1,"value":0}],"gold":0,"name":"","note":"","params":[100,0,10,10,10,10,10,10]},
{"id":3,"actions":[{"conditionParam1":0,"conditionParam2":0,"conditionType":0,"rating":5,"skillId":1}],"battlerHue":0,"battlerName":"","dropItems":[{"dataId":1,"denominator":1,"kind":0},{"dataId":1,"denominator":1,"kind":0},{"dataId":1,"denominator":1,"kind":0}],"exp":0,"traits":[{"code":22,"dataId":0,"value":0.95},{"code":22,"dataId":1,"value":0.05},{"code":31,"dataId":1,"value":0}],"gold":0,"name":"","note":"","params":[100,0,10,10,10,10,10,10]},
{"id":4,"actions":[{"conditionParam1":0,"conditionParam2":0,"conditionType":0,"rating":5,"skillId":1}],"battlerHue":0,"battlerName":"Soldier","dropItems":[{"dataId":1,"denominator":1,"kind":0},{"dataId":1,"denominator":1,"kind":0},{"dataId":1,"denominator":1,"kind":0}],"exp":0,"traits":[{"code":11,"dataId":5,"value":1},{"code":11,"dataId":3,"value":0.5},{"code":11,"dataId":4,"value":1.5},{"code":31,"dataId":5,"value":1},{"code":22,"dataId":0,"value":1}],"gold":0,"name":"哲学兵【γ】","note":"","params":[110,0,30,10,10,10,10,10]},
{"id":5,"actions":[{"conditionParam1":0,"conditionParam2":0,"conditionType":0,"rating":5,"skillId":1}],"battlerHue":0,"battlerName":"","dropItems":[{"dataId":1,"denominator":1,"kind":0},{"dataId":1,"denominator":1,"kind":0},{"dataId":1,"denominator":1,"kind":0}],"exp":0,"traits":[{"code":22,"dataId":0,"value":0.95},{"code":22,"dataId":1,"value":0.05},{"code":31,"dataId":1,"value":0}],"gold":0,"name":"","note":"","params":[100,0,10,10,10,10,10,10]},
{"id":6,"actions":[{"conditionParam1":0,"conditionParam2":0,"conditionType":0,"rating":5,"skillId":1}],"battlerHue":0,"battlerName":"","dropItems":[{"dataId":1,"denominator":1,"kind":0},{"dataId":1,"denominator":1,"kind":0},{"dataId":1,"denominator":1,"kind":0}],"exp":0,"traits":[{"code":22,"dataId":0,"value":0.95},{"code":22,"dataId":1,"value":0.05},{"code":31,"dataId":1,"value":0}],"gold":0,"name":"","note":"","params":[100,0,10,10,10,10,10,10]},
{"id":7,"actions":[{"conditionParam1":0,"conditionParam2":0,"conditionType":0,"rating":5,"skillId":1}],"battlerHue":0,"battlerName":"Willowisp","dropItems":[{"dataId":1,"denominator":1,"kind":0},{"dataId":1,"denominator":1,"kind":0},{"dataId":1,"denominator":1,"kind":0}],"exp":0,"traits":[{"code":11,"dataId":4,"value":1},{"code":11,"dataId":5,"value":0.5},{"code":11,"dataId":3,"value":1.5},{"code":31,"dataId":4,"value":1},{"code":22,"dataId":0,"value":1}],"gold":0,"name":"スピリット【β】","note":"","params":[160,100,30,10,20,20,10,10]},
{"id":8,"actions":[{"conditionParam1":0,"conditionParam2":0,"conditionType":0,"rating":5,"skillId":1}],"battlerHue":0,"battlerName":"","dropItems":[{"dataId":1,"denominator":1,"kind":0},{"dataId":1,"denominator":1,"kind":0},{"dataId":1,"denominator":1,"kind":0}],"exp":0,"traits":[{"code":22,"dataId":0,"value":0.95},{"code":22,"dataId":1,"value":0.05},{"code":31,"dataId":1,"value":0}],"gold":0,"name":"","note":"","params":[100,0,10,10,10,10,10,10]},
{"id":9,"actions":[{"conditionParam1":0,"conditionParam2":0,"conditionType":0,"rating":5,"skillId":1}],"battlerHue":0,"battlerName":"","dropItems":[{"dataId":1,"denominator":1,"kind":0},{"dataId":1,"denominator":1,"kind":0},{"dataId":1,"denominator":1,"kind":0}],"exp":0,"traits":[{"code":22,"dataId":0,"value":0.95},{"code":22,"dataId":1,"value":0.05},{"code":31,"dataId":1,"value":0}],"gold":0,"name":"","note":"","params":[100,0,10,10,10,10,10,10]},
{"id":10,"actions":[{"conditionParam1":0,"conditionParam2":0,"conditionType":0,"rating":5,"skillId":1}],"battlerHue":0,"battlerName":"","dropItems":[{"dataId":1,"denominator":1,"kind":0},{"dataId":1,"denominator":1,"kind":0},{"dataId":1,"denominator":1,"kind":0}],"exp":0,"traits":[{"code":22,"dataId":0,"value":0.95},{"code":22,"dataId":1,"value":0.05},{"code":31,"dataId":1,"value":0}],"gold":0,"name":"","note":"","params":[100,0,10,10,10,10,10,10]},
{"id":11,"actions":[{"conditionParam1":0,"conditionParam2":0,"conditionType":0,"rating":5,"skillId":1}],"battlerHue":0,"battlerName":"Behemoth","dropItems":[{"dataId":1,"denominator":1,"kind":0},{"dataId":1,"denominator":1,"kind":0},{"dataId":1,"denominator":1,"kind":0}],"exp":0,"traits":[{"code":11,"dataId":3,"value":1},{"code":11,"dataId":4,"value":0.5},{"code":11,"dataId":5,"value":1.5},{"code":31,"dataId":3,"value":1},{"code":22,"dataId":0,"value":1}],"gold":0,"name":"ベビモス【α】","note":"","params":[500,0,35,15,10,10,10,10]},
{"id":12,"actions":[{"conditionParam1":0,"conditionParam2":0,"conditionType":0,"rating":5,"skillId":1}],"battlerHue":0,"battlerName":"","dropItems":[{"dataId":1,"denominator":1,"kind":0},{"dataId":1,"denominator":1,"kind":0},{"dataId":1,"denominator":1,"kind":0}],"exp":0,"traits":[{"code":22,"dataId":0,"value":0.95},{"code":22,"dataId":1,"value":0.05},{"code":31,"dataId":1,"value":0}],"gold":0,"name":"","note":"","params":[100,0,10,10,10,10,10,10]},
{"id":13,"actions":[{"conditionParam1":0,"conditionParam2":0,"conditionType":0,"rating":5,"skillId":1}],"battlerHue":0,"battlerName":"","dropItems":[{"dataId":1,"denominator":1,"kind":0},{"dataId":1,"denominator":1,"kind":0},{"dataId":1,"denominator":1,"kind":0}],"exp":0,"traits":[{"code":22,"dataId":0,"value":0.95},{"code":22,"dataId":1,"value":0.05},{"code":31,"dataId":1,"value":0}],"gold":0,"name":"","note":"","params":[100,0,10,10,10,10,10,10]},
{"id":14,"actions":[{"conditionParam1":0,"conditionParam2":0,"conditionType":0,"rating":5,"skillId":1}],"battlerHue":0,"battlerName":"","dropItems":[{"dataId":1,"denominator":1,"kind":0},{"dataId":1,"denominator":1,"kind":0},{"dataId":1,"denominator":1,"kind":0}],"exp":0,"traits":[{"code":22,"dataId":0,"value":0.95},{"code":22,"dataId":1,"value":0.05},{"code":31,"dataId":1,"value":0}],"gold":0,"name":"","note":"","params":[100,0,10,10,10,10,10,10]},
{"id":15,"actions":[{"conditionParam1":0,"conditionParam2":0,"conditionType":0,"rating":5,"skillId":1}],"battlerHue":0,"battlerName":"","dropItems":[{"dataId":1,"denominator":1,"kind":0},{"dataId":1,"denominator":1,"kind":0},{"dataId":1,"denominator":1,"kind":0}],"exp":0,"traits":[{"code":22,"dataId":0,"value":0.95},{"code":22,"dataId":1,"value":0.05},{"code":31,"dataId":1,"value":0}],"gold":0,"name":"","note":"","params":[100,0,10,10,10,10,10,10]},
{"id":16,"actions":[{"conditionParam1":0,"conditionParam2":0,"conditionType":0,"rating":5,"skillId":1}],"battlerHue":0,"battlerName":"","dropItems":[{"dataId":1,"denominator":1,"kind":0},{"dataId":1,"denominator":1,"kind":0},{"dataId":1,"denominator":1,"kind":0}],"exp":0,"traits":[{"code":22,"dataId":0,"value":0.95},{"code":22,"dataId":1,"value":0.05},{"code":31,"dataId":1,"value":0}],"gold":0,"name":"","note":"","params":[100,0,10,10,10,10,10,10]},
{"id":17,"actions":[{"conditionParam1":0,"conditionParam2":0,"conditionType":0,"rating":5,"skillId":1}],"battlerHue":0,"battlerName":"","dropItems":[{"dataId":1,"denominator":1,"kind":0},{"dataId":1,"denominator":1,"kind":0},{"dataId":1,"denominator":1,"kind":0}],"exp":0,"traits":[{"code":22,"dataId":0,"value":0.95},{"code":22,"dataId":1,"value":0.05},{"code":31,"dataId":1,"value":0}],"gold":0,"name":"","note":"","params":[100,0,10,10,10,10,10,10]},
{"id":18,"actions":[{"conditionParam1":0,"conditionParam2":0,"conditionType":0,"rating":5,"skillId":1}],"battlerHue":0,"battlerName":"","dropItems":[{"dataId":1,"denominator":1,"kind":0},{"dataId":1,"denominator":1,"kind":0},{"dataId":1,"denominator":1,"kind":0}],"exp":0,"traits":[{"code":22,"dataId":0,"value":0.95},{"code":22,"dataId":1,"value":0.05},{"code":31,"dataId":1,"value":0}],"gold":0,"name":"","note":"","params":[100,0,10,10,10,10,10,10]},
{"id":19,"actions":[{"conditionParam1":0,"conditionParam2":0,"conditionType":0,"rating":5,"skillId":1}],"battlerHue":0,"battlerName":"","dropItems":[{"dataId":1,"denominator":1,"kind":0},{"dataId":1,"denominator":1,"kind":0},{"dataId":1,"denominator":1,"kind":0}],"exp":0,"traits":[{"code":22,"dataId":0,"value":0.95},{"code":22,"dataId":1,"value":0.05},{"code":31,"dataId":1,"value":0}],"gold":0,"name":"","note":"","params":[100,0,10,10,10,10,10,10]},
{"id":20,"actions":[{"conditionParam1":0,"conditionParam2":0,"conditionType":0,"rating":5,"skillId":1}],"battlerHue":0,"battlerName":"","dropItems":[{"dataId":1,"denominator":1,"kind":0},{"dataId":1,"denominator":1,"kind":0},{"dataId":1,"denominator":1,"kind":0}],"exp":0,"traits":[{"code":22,"dataId":0,"value":0.95},{"code":22,"dataId":1,"value":0.05},{"code":31,"dataId":1,"value":0}],"gold":0,"name":"","note":"","params":[100,0,10,10,10,10,10,10]},
{"id":21,"actions":[{"conditionParam1":0,"conditionParam2":0,"conditionType":0,"rating":5,"skillId":1}],"battlerHue":0,"battlerName":"Orc","dropItems":[{"dataId":1,"denominator":1,"kind":0},{"dataId":1,"denominator":1,"kind":0},{"dataId":1,"denominator":1,"kind":0}],"exp":0,"traits":[{"code":11,"dataId":3,"value":1},{"code":11,"dataId":4,"value":0.5},{"code":11,"dataId":5,"value":1.5},{"code":31,"dataId":3,"value":1},{"code":22,"dataId":0,"value":1}],"gold":0,"name":"森オーク【α】","note":"","params":[60,0,20,10,10,10,10,10]},
{"id":22,"actions":[{"conditionParam1":0,"conditionParam2":0,"conditionType":0,"rating":5,"skillId":1}],"battlerHue":0,"battlerName":"Ghost","dropItems":[{"dataId":1,"denominator":1,"kind":0},{"dataId":1,"denominator":1,"kind":0},{"dataId":1,"denominator":1,"kind":0}],"exp":0,"traits":[{"code":11,"dataId":5,"value":1},{"code":11,"dataId":3,"value":0.5},{"code":11,"dataId":4,"value":1.5},{"code":31,"dataId":3,"value":1},{"code":22,"dataId":0,"value":1}],"gold":0,"name":"森幽霊【γ】","note":"","params":[300,0,20,10,10,10,10,10]},
{"id":23,"actions":[{"conditionParam1":0,"conditionParam2":0,"conditionType":0,"rating":5,"skillId":1}],"battlerHue":0,"battlerName":"","dropItems":[{"dataId":1,"denominator":1,"kind":0},{"dataId":1,"denominator":1,"kind":0},{"dataId":1,"denominator":1,"kind":0}],"exp":0,"traits":[{"code":22,"dataId":0,"value":0.95},{"code":22,"dataId":1,"value":0.05},{"code":31,"dataId":1,"value":0}],"gold":0,"name":"","note":"","params":[100,0,10,10,10,10,10,10]},
{"id":24,"actions":[{"conditionParam1":0,"conditionParam2":0,"conditionType":0,"rating":5,"skillId":1}],"battlerHue":0,"battlerName":"","dropItems":[{"dataId":1,"denominator":1,"kind":0},{"dataId":1,"denominator":1,"kind":0},{"dataId":1,"denominator":1,"kind":0}],"exp":0,"traits":[{"code":22,"dataId":0,"value":0.95},{"code":22,"dataId":1,"value":0.05},{"code":31,"dataId":1,"value":0}],"gold":0,"name":"","note":"","params":[100,0,10,10,10,10,10,10]},
{"id":25,"actions":[{"conditionParam1":0,"conditionParam2":0,"conditionType":0,"rating":5,"skillId":1}],"battlerHue":0,"battlerName":"","dropItems":[{"dataId":1,"denominator":1,"kind":0},{"dataId":1,"denominator":1,"kind":0},{"dataId":1,"denominator":1,"kind":0}],"exp":0,"traits":[{"code":22,"dataId":0,"value":0.95},{"code":22,"dataId":1,"value":0.05},{"code":31,"dataId":1,"value":0}],"gold":0,"name":"","note":"","params":[100,0,10,10,10,10,10,10]},
{"id":26,"actions":[{"conditionParam1":0,"conditionParam2":0,"conditionType":0,"rating":5,"skillId":1}],"battlerHue":0,"battlerName":"","dropItems":[{"dataId":1,"denominator":1,"kind":0},{"dataId":1,"denominator":1,"kind":0},{"dataId":1,"denominator":1,"kind":0}],"exp":0,"traits":[{"code":22,"dataId":0,"value":0.95},{"code":22,"dataId":1,"value":0.05},{"code":31,"dataId":1,"value":0}],"gold":0,"name":"","note":"","params":[100,0,10,10,10,10,10,10]},
{"id":27,"actions":[{"conditionParam1":0,"conditionParam2":0,"conditionType":0,"rating":5,"skillId":1}],"battlerHue":0,"battlerName":"","dropItems":[{"dataId":1,"denominator":1,"kind":0},{"dataId":1,"denominator":1,"kind":0},{"dataId":1,"denominator":1,"kind":0}],"exp":0,"traits":[{"code":22,"dataId":0,"value":0.95},{"code":22,"dataId":1,"value":0.05},{"code":31,"dataId":1,"value":0}],"gold":0,"name":"","note":"","params":[100,0,10,10,10,10,10,10]}
]